armonik_cli/__init__.py
armonik_cli/admin.py
armonik_cli/bench.py
armonik_cli/models.py
armonik_cli/result.py
armonik_cli/session.py
armonik_cli/task.py
armonik_cli-1.2.0.dist-info/AUTHORS.rst
armonik_cli-1.2.0.dist-info/LICENSE
armonik_cli-1.2.0.dist-info/METADATA
armonik_cli-1.2.0.dist-info/WHEEL
armonik_cli-1.2.0.dist-info/entry_points.txt
armonik_cli-1.2.0.dist-info/top_level.txt
armonik_cli-1.2.0.dist-info/RECORD
