Metadata-Version: 2.1
Name: armonik-cli
Version: 1.2.0
Summary: A CLI to administrate ArmoniK orchestrator
License: MIT License
Project-URL: Homepage, https://github.com/jeremyzyngeraneo/rncp
Keywords: cloud,HTC
Classifier: Programming Language :: Python :: 3
Requires-Python: >=3.8
License-File: LICENSE
License-File: AUTHORS.rst
Requires-Dist: armonik >=3.15.0
Requires-Dist: sqlalchemy
Requires-Dist: psycopg2-binary
Requires-Dist: python-dotenv
Requires-Dist: alembic
Provides-Extra: dev
Requires-Dist: mypy ; extra == 'dev'
Requires-Dist: ruff ; extra == 'dev'
Provides-Extra: tests
Requires-Dist: coverage ; extra == 'tests'
Requires-Dist: pytest ; extra == 'tests'
Requires-Dist: pytest-cov ; extra == 'tests'
Requires-Dist: requests ; extra == 'tests'
Requires-Dist: pytest-benchmark[histogram] ; extra == 'tests'
